<graph>
    <id>g0</id>
    <name>Simple testing graph</name>
    <nodes>
        <node>
            <id>a</id>
            <name>A</name>
        </node>
        <node>
            <id>b</id>
            <name>B</name>
        </node>
        <node>
            <id>c</id>
            <name>C</name>
        </node>
        <node>
            <id>d</id>
            <name>D</name>
        </node>
        <node>
            <id>e</id>
            <name>E</name>
        </node>
    </nodes>
    <edges>
        <edge>
            <id>e12</id>
            <from>a</from>
            <to>b</to>
            <cost>10</cost>
        </edge>
        <edge>
            <id>e13</id>
            <from>a</from>
            <to>c</to>
            <cost>5</cost>
        </edge>
        <edge>
            <id>e24</id>
            <from>b</from>
            <to>d</to>
            <cost>10</cost>
        </edge>
        <edge>
            <id>e34</id>
            <from>c</from>
            <to>d</to>
            <cost>20</cost>
        </edge>
        <edge>
            <id>e45</id>
            <from>d</from>
            <to>e</to>
            <cost>5</cost>
        </edge>
        <edge>
            <id>e15</id>
            <from>a</from>
            <to>e</to>
            <cost>50</cost>
        </edge>
        <edge>
            <id>e35</id>
            <from>c</from>
            <to>e</to>
            <cost>30</cost>
        </edge>
    </edges>
</graph>